[
    {
        "question": "q0",
        "choice": [
            "a0",
            "a1",
            "a2",
            "a3"
        ],
        "correct": 0,
        "explanation": "e0"
    },
    {
        "question": "q1",
        "choice": [
            "a0",
            "a1",
            "a2",
            "a3"
        ],
        "correct": 1,
        "explanation": "e1"
    },
    {
        "question": "q2",
        "choice": [
            "a0",
            "a1",
            "a2",
            "a3"
        ],
        "correct": 2,
        "explanation": "e2"
    },
    {
        "question": "q3",
        "choice": [
            "a0",
            "a1",
            "a2",
            "a3"
        ],
        "correct": 3,
        "explanation": "e3"
    }
]
